{
	"1": {
		"game_score_0": 0,
		"game_score_1": 0,
		"game_score_2": 0,
		"game_score_3": 0,
		"game_score_4": 0,
		"game_score_5": 0,
		"game_score_6": 0
	},
	"2": {
		"game_score_0": 0,
		"game_score_1": 0,
		"game_score_2": 0,
		"game_score_3": 0,
		"game_score_4": 0,
		"game_score_5": 0,
		"game_score_6": 0
	},
	"3": {
		"game_score_0": 0,
		"game_score_1": 0,
		"game_score_2": 0,
		"game_score_3": 0,
		"game_score_4": 0,
		"game_score_5": 0,
		"game_score_6": 0
	},
	"4": {
		"game_score_0": 0,
		"game_score_1": 0,
		"game_score_2": 0,
		"game_score_3": 0,
		"game_score_4": 0,
		"game_score_5": 0,
		"game_score_6": 0
	}
}
